.gitignore
LICENSE.txt
README
distribute_setup.py
setup.py
Pyrana.egg-info/PKG-INFO
Pyrana.egg-info/SOURCES.txt
Pyrana.egg-info/dependency_links.txt
Pyrana.egg-info/entry_points.txt
Pyrana.egg-info/not-zip-safe
Pyrana.egg-info/requires.txt
Pyrana.egg-info/top_level.txt
pyrana/Pyrana.py
pyrana/__init__.py
pyrana/gui.py
pyrana/player.py
pyrana/players/__init__.py
pyrana/players/pygameplayer.py
pyrana/players/pygletplayer.py
pyrana/players/pygstplayer.py
pyrana/playlists/__init__.py
pyrana/playlists/sanerandalbums.py
pyrana/plugins/__init__.py
pyrana/plugins/notify.py
pyrana/plugins/pidginstatus.py
pyrana/resources/__init__.py
pyrana/resources/options.ini
pyrana/resources/playing.png
pyrana/resources/pyrana.cfg
pyrana/resources/stopped.png
pyrana/uis/__init__.py
pyrana/uis/gtk2.py