Metadata-Version: 1.0
Name: Pyrana
Version: 2.0.0
Summary: a minimalistic mp3 player
Home-page: http://github.com/jdodds/pyrana
Author: Jeremiah Dodds
Author-email: jeremiah.dodds@gmail.com
License: LICENSE.txt
Download-URL: http://github.com/jdodds/pyrana/downloads
Keywords: music mp3 ogg mp4 musicplayer player
Platform: UNKNOWN
Classifier: Development Status :: 5 - Production/Stable
Classifier: Environment :: X11 Applications :: GTK
Classifier: Intended Audience :: End Users/Desktop
Classifier: License :: OSI Approved :: BSD License
Classifier: Natural Language :: English
Classifier: Operating System :: POSIX :: Linux
Classifier: Programming Language :: Python :: 2.7
Classifier: Topic :: Multimedia
Classifier: Topic :: Multimedia :: Sound/Audio :: Players
